codeEditorSDK/__init__.py
codeEditorSDK/exception.py
codeEditorSDK/factories.py
codeEditorSDK/core/EditBuilder.py
codeEditorSDK/core/__init__.py
codeEditorSDK/core/codeEditor.py
codeEditorSDK/utils/ASTUnrollHelper.py
codeEditorSDK/utils/__init__.py
codeEditorSDK/utils/indent.py
codeEditorSDK/utils/validation.py
codeeditorsdk-0.1.2.dist-info/METADATA
codeeditorsdk-0.1.2.dist-info/WHEEL
codeeditorsdk-0.1.2.dist-info/top_level.txt
codeeditorsdk-0.1.2.dist-info/RECORD
